HISTORY.md
csvblend/__init__.py
csvblend/csvblend.py
csvblend/models.py
csvblend/utils.py
csvblend-0.2.0.dist-info/LICENSE
csvblend-0.2.0.dist-info/METADATA
csvblend-0.2.0.dist-info/WHEEL
csvblend-0.2.0.dist-info/RECORD
